command_queue/__init__.py
command_queue/commands.py
command_queue-0.2.0.dist-info/METADATA
command_queue-0.2.0.dist-info/WHEEL
command_queue-0.2.0.dist-info/licenses/LICENSE
command_queue-0.2.0.dist-info/RECORD
